ABOUT.txt
License.txt
MANIFEST
MANIFEST.in
README.txt
Ragnarok License.txt
__init__.py
py2exe_setup.py
setup.py
todo.txt
wordgolf.py
WordGolf.egg-info/PKG-INFO
WordGolf.egg-info/SOURCES.txt
WordGolf.egg-info/dependency_links.txt
WordGolf.egg-info/top_level.txt
game/__init__.py
game/common.py
game/escapepage.py
game/game.py
game/gameover.py
game/gamestart.py
game/golfer.py
game/graphical.py
game/helppage.py
game/keypad.py
game/scorespage.py
game/theme.py
graphics/big_button.png
graphics/button1.png
graphics/button2.png
graphics/button_back.png
graphics/course1.png
graphics/course1.svg
graphics/endgamepage.png
graphics/escapepage.png
graphics/game1_1.png
graphics/game1_2.png
graphics/game2_1.png
graphics/game2_2.png
graphics/game3_1.png
graphics/game3_2.png
graphics/grass.png
graphics/helppage.png
graphics/hole.png
graphics/hole1.png
graphics/letter_1.png
graphics/letter_2.png
graphics/logo.png
graphics/past.png
graphics/sand.png
graphics/scorespage.png
graphics/start_bg.png
graphics/water.png
graphics/wordgolf.ico
serge/__init__.py
serge/actor.py
serge/camera.py
serge/common.py
serge/engine.py
serge/events.py
serge/geometry.py
serge/input.py
serge/physical.py
serge/registry.py
serge/render.py
serge/serialize.py
serge/simplevecs.py
serge/sound.py
serge/visual.py
serge/world.py
serge/zone.py
serge/blocks/__init__.py
serge/blocks/effects.py
serge/blocks/layout.py
serge/blocks/scores.py
serge/blocks/themes.py
serge/blocks/utils.py
serge/blocks/visualblocks.py
sound/106727__kantouth__CARTOON_BING_LOW.wav
sound/109663__grunz__success_low.wav
sound/13945__adcbicycle__17.wav
sound/30602__acclivity__Goblet_G_Loud.wav
sound/32073__hello_flowers__Splash_Request.wav
sound/43606__FreqMan__sandbag_3_.wav
sound/51713__BristolStories__u_chimes_short1.mp3
sound/85999__nextmaking__Jump_from_the_sand_ground_2.wav
sound/91926__Corsica_S__ding.wav
sound/94120__BMacZero__Mechanical1.wav
sound/96137__BMacZero__Thud2.wav
sound/badletter.wav
sound/begin.wav
sound/end_game.wav
sound/error.wav
sound/good_hole.wav
sound/hole.wav
sound/letter.wav
sound/poor_hole.wav
sound/sand.wav
sound/start.wav
sound/unletter.wav
