Metadata-Version: 1.0
Name: WordGolf
Version: 0.2.2
Summary: Word game that combines Boggle-like word finding with golf.
Home-page: http://www.perpetualpyramid/wordgolf.html
Author: Paul Paterson
Author-email: ppaterson@gmail.com
License: UNKNOWN
Download-URL: http://perpetualpyramid.com/WordGolf-0.2.2-py2.6.tar.gz
Platform: UNKNOWN
Classifier: Programming Language :: Python
Classifier: Programming Language :: Python :: 2
Classifier: Development Status :: 4 - Beta
Classifier: Environment :: Other Environment
Classifier: Intended Audience :: End Users/Desktop
Classifier: License :: OSI Approved :: GNU Library or Lesser General Public License (LGPL)
Classifier: Operating System :: OS Independent
Classifier: Topic :: Games/Entertainment
Classifier: Topic :: Games/Entertainment :: Puzzle Games
